{
  "userChats": {
    "426818020": {
      "id": 426818020,
      "username": "dimasiaaa",
      "first_name": "Микки Маус",
      "last_name": "",
      "joined_at": "2025-09-24T17:56:53.333Z",
      "last_activity": "2025-09-24T18:04:15.777Z"
    },
    "594143385": {
      "id": 594143385,
      "username": "SASH999666LUDOGOLIK",
      "first_name": "LUDOGOLIK",
      "language_code": "ru",
      "joined_at": "2025-09-25T00:58:57.528Z",
      "last_activity": "2025-09-25T00:59:05.325Z"
    },
    "1097210873": {
      "id": 1097210873,
      "username": "chupachypik",
      "first_name": "🍭̶Ч̶У̶П̶А̶ ̶",
      "last_name": "Ч̶У̶П̶И̶К🍭",
      "joined_at": "2025-09-25T03:20:08.949Z",
      "last_activity": "2025-09-25T03:23:01.205Z"
    },
    "1777213824": {
      "id": 1777213824,
      "username": "NSDcode",
      "first_name": "Zulu",
      "last_name": "NSD",
      "language_code": "ru",
      "joined_at": "2025-09-10T17:10:33.867Z",
      "last_activity": "2025-09-26T16:54:51.345Z"
    },
    "6770360650": {
      "id": 6770360650,
      "username": "Zuluzozo",
      "first_name": "Киборг Убийца",
      "language_code": "ru",
      "joined_at": "2025-09-10T17:39:57.669Z",
      "last_activity": "2025-09-10T17:48:50.251Z"
    },
    "7670761239": {
      "id": 7670761239,
      "username": "Seregovr",
      "first_name": "Имя",
      "last_name": "Фамилия",
      "language_code": "ru",
      "joined_at": "2025-09-24T18:13:45.259Z",
      "last_activity": "2025-09-25T03:13:20.068Z"
    },
    "6976083104": {
      "id": 6976083104,
      "username": "vadinara",
      "first_name": "Billi",
      "last_name": "Good",
      "language_code": "ru",
      "joined_at": "2025-09-24T18:15:50.382Z",
      "last_activity": "2025-09-24T18:15:50.382Z"
    },
    "6666297900": {
      "id": 6666297900,
      "username": "rb_Kirochka",
      "first_name": "Кира",
      "language_code": "ru",
      "joined_at": "2025-09-24T18:16:47.619Z",
      "last_activity": "2025-09-25T05:06:42.225Z"
    },
    "5905497905": {
      "id": 5905497905,
      "username": "LUDOMYSH",
      "first_name": "LUDOMYSH",
      "language_code": "ru",
      "joined_at": "2025-09-25T01:02:05.696Z",
      "last_activity": "2025-09-25T01:02:11.492Z"
    },
    "8088072087": {
      "id": 8088072087,
      "username": "LUDOMAN_ONLINE",
      "first_name": "𝐋𝐔𝐃𝐎𝐌𝐀𝐍_𝐎𝐍𝐋𝐈𝐍𝐄",
      "language_code": "ru",
      "joined_at": "2025-09-25T10:53:08.062Z",
      "last_activity": "2025-09-25T11:04:34.460Z"
    }
  },
  "userSettings": {
    "426818020": {
      "hiddenCasinos": [],
      "notifications": true,
      "theme": "dark",
      "hasLiveAccess": false,
      "viewMode": "compact"
    },
    "594143385": {
      "hiddenCasinos": [],
      "notifications": true,
      "theme": "dark",
      "hasLiveAccess": false,
      "viewMode": "compact"
    },
    "1097210873": {
      "hiddenCasinos": [],
      "notifications": true,
      "theme": "dark",
      "hasLiveAccess": false,
      "viewMode": "compact"
    },
    "1777213824": {
      "hiddenCasinos": [],
      "notifications": true,
      "theme": "dark",
      "hasLiveAccess": true,
      "viewMode": "compact",
      "contestState": null
    },
    "6770360650": {
      "hiddenCasinos": [
        1,
        38
      ],
      "notifications": true,
      "theme": "dark",
      "hasLiveAccess": true,
      "viewMode": "compact"
    },
    "7670761239": {
      "hiddenCasinos": [],
      "notifications": true,
      "theme": "dark",
      "hasLiveAccess": false
    },
    "6976083104": {
      "hiddenCasinos": [],
      "notifications": true,
      "theme": "dark",
      "hasLiveAccess": false
    },
    "6666297900": {
      "hiddenCasinos": [],
      "notifications": true,
      "theme": "dark",
      "hasLiveAccess": false,
      "viewMode": "full"
    },
    "5905497905": {
      "hiddenCasinos": [],
      "notifications": true,
      "theme": "dark",
      "hasLiveAccess": false
    },
    "8088072087": {
      "hiddenCasinos": [],
      "notifications": true,
      "theme": "dark",
      "hasLiveAccess": false,
      "viewMode": "full"
    }
  },
  "giveaways": [],
  "pendingApprovals": [],
  "referralData": {
    "1777213824": {
      "referrals": [
        6666297900,
        8088072087
      ],
      "totalEarned": 20
    },
    "7670761239": {
      "referrals": [
        6976083104
      ],
      "totalEarned": 10
    },
    "6976083104": {
      "referredBy": 7670761239,
      "referrals": [],
      "totalEarned": 0
    },
    "6666297900": {
      "referredBy": 1777213824,
      "referrals": [],
      "totalEarned": 0
    },
    "8088072087": {
      "referredBy": 1777213824,
      "referrals": [],
      "totalEarned": 0
    }
  },
  "lastUpdated": "2025-09-27T01:35:43.297Z"
}